docs2epub/__init__.py
docs2epub/cli.py
docs2epub/docusaurus_next.py
docs2epub/epub.py
docs2epub/kindle_html.py
docs2epub/model.py
docs2epub/pandoc_epub2.py
docs2epub-0.1.2.dist-info/METADATA
docs2epub-0.1.2.dist-info/WHEEL
docs2epub-0.1.2.dist-info/entry_points.txt
docs2epub-0.1.2.dist-info/RECORD
