Metadata-Version: 2.4
Name: docs2epub
Version: 0.1.2
Summary: Turn documentation sites into an EPUB (Kindle-friendly).
Author: Breno Brito
License: MIT
Requires-Python: >=3.12
Requires-Dist: beautifulsoup4>=4.14.3
Requires-Dist: ebooklib>=0.20
Requires-Dist: lxml>=6.0.2
Requires-Dist: requests>=2.32.5
Provides-Extra: dev
Requires-Dist: pytest-cov>=4.1.0; extra == 'dev'
Requires-Dist: pytest>=8.0.0; extra == 'dev'
